autots/__init__.py
autots/datasets/__init__.py
autots/datasets/_base.py
autots/datasets/fred.py
autots/datasets/synthetic.py
autots/datasets/data/covid_daily.zip
autots/datasets/data/eia_weekly.zip
autots/datasets/data/fred_monthly.zip
autots/datasets/data/fred_yearly.zip
autots/datasets/data/holidays.zip
autots/datasets/data/traffic_hourly.zip
autots/evaluator/__init__.py
autots/evaluator/anomaly_detector.py
autots/evaluator/auto_model.py
autots/evaluator/auto_ts.py
autots/evaluator/benchmark.py
autots/evaluator/event_forecasting.py
autots/evaluator/feature_detector.py
autots/evaluator/metrics.py
autots/evaluator/validation.py
autots/mcp/README.md
autots/mcp/__init__.py
autots/mcp/mosaic_profile_template.json
autots/mcp/server.py
autots/models/__init__.py
autots/models/arch.py
autots/models/base.py
autots/models/basics.py
autots/models/cassandra.py
autots/models/composite.py
autots/models/deepssm.py
autots/models/dnn.py
autots/models/ensemble.py
autots/models/gluonts.py
autots/models/matrix_var.py
autots/models/mlensemble.py
autots/models/model_list.py
autots/models/neural_forecast.py
autots/models/prophet.py
autots/models/pytorch.py
autots/models/sklearn.py
autots/models/statsmodels.py
autots/models/tide.py
autots/templates/__init__.py
autots/templates/general.py
autots/tools/__init__.py
autots/tools/anomaly_utils.py
autots/tools/autoencoder.py
autots/tools/bayesian_regression.py
autots/tools/calendar.py
autots/tools/changepoints.py
autots/tools/cointegration.py
autots/tools/constraint.py
autots/tools/cpu_count.py
autots/tools/fast_kalman.py
autots/tools/fast_kalman_params.py
autots/tools/fft.py
autots/tools/fir_filter.py
autots/tools/g7xx_codec.py
autots/tools/hierarchial.py
autots/tools/holiday.py
autots/tools/impute.py
autots/tools/kalman.py
autots/tools/lunar.py
autots/tools/mocks.py
autots/tools/percentile.py
autots/tools/plotting.py
autots/tools/probabilistic.py
autots/tools/profile.py
autots/tools/regressor.py
autots/tools/seasonal.py
autots-1.0.1.dist-info/licenses/LICENSE
autots-1.0.1.dist-info/METADATA
autots-1.0.1.dist-info/WHEEL
autots-1.0.1.dist-info/entry_points.txt
autots-1.0.1.dist-info/top_level.txt
autots-1.0.1.dist-info/RECORD
