Metadata-Version: 2.4
Name: autots
Version: 1.0.1
Summary: Automated Time Series Forecasting
Home-page: https://github.com/winedarksea/AutoTS
Author: Colin Catlin
Author-email: Colin Catlin <colin.catlin@gmail.com>
License: MIT License
Project-URL: Homepage, https://github.com/winedarksea/AutoTS
Project-URL: Bug Tracker, https://github.com/winedarksea/AutoTS/issues
Classifier: Programming Language :: Python :: 3
Classifier: License :: OSI Approved :: MIT License
Classifier: Operating System :: OS Independent
Requires-Python: >=3.9
License-File: LICENSE
Requires-Dist: numpy>=1.21.6
Requires-Dist: pandas>=1.1.0
Requires-Dist: statsmodels>=0.13.0
Requires-Dist: scikit-learn>=1.0.0
Provides-Extra: additional
Requires-Dist: holidays>=0.9; extra == "additional"
Requires-Dist: prophet>=1.0.0; extra == "additional"
Requires-Dist: fredapi; extra == "additional"
Requires-Dist: tensorflow; extra == "additional"
Requires-Dist: xgboost>=1.6; extra == "additional"
Requires-Dist: lightgbm; extra == "additional"
Requires-Dist: joblib; extra == "additional"
Requires-Dist: scipy; extra == "additional"
Requires-Dist: arch; extra == "additional"
Requires-Dist: numexpr; extra == "additional"
Requires-Dist: bottleneck; extra == "additional"
Requires-Dist: yfinance; extra == "additional"
Requires-Dist: pytrends; extra == "additional"
Requires-Dist: matplotlib; extra == "additional"
Requires-Dist: requests; extra == "additional"
Requires-Dist: seaborn; extra == "additional"
Provides-Extra: mcp
Requires-Dist: holidays>=0.9; extra == "mcp"
Requires-Dist: fredapi; extra == "mcp"
Requires-Dist: lightgbm; extra == "mcp"
Requires-Dist: joblib; extra == "mcp"
Requires-Dist: scipy; extra == "mcp"
Requires-Dist: numexpr; extra == "mcp"
Requires-Dist: bottleneck; extra == "mcp"
Requires-Dist: yfinance; extra == "mcp"
Requires-Dist: pytrends; extra == "mcp"
Requires-Dist: matplotlib; extra == "mcp"
Requires-Dist: requests; extra == "mcp"
Requires-Dist: seaborn; extra == "mcp"
Requires-Dist: mcp>=1.0.0; extra == "mcp"
Dynamic: author
Dynamic: home-page
Dynamic: license-file
Dynamic: requires-python
